apikey/__init__.py
apikey/db.py
apikey/dependencies.py
apikey/manager.py
apikey/models.py
apikey/router.py
apikey/service.py
apikey/utils.py
beanone_apikey-0.3.0.dist-info/METADATA
beanone_apikey-0.3.0.dist-info/WHEEL
beanone_apikey-0.3.0.dist-info/entry_points.txt
beanone_apikey-0.3.0.dist-info/licenses/LICENSE
beanone_apikey-0.3.0.dist-info/RECORD
